cryptolith/__init__.py
cryptolith/bcc_engine.cpython-314-aarch64-linux-musl.so
cryptolith/bcc_static_linker.py
cryptolith/cli.py
cryptolith/compiler.py
cryptolith/core.cpython-314-aarch64-linux-musl.so
cryptolith/license_manager.cpython-314-aarch64-linux-musl.so
cryptolith/obfuscator.cpython-314-aarch64-linux-musl.so
cryptolith/profiler.py
cryptolith/rthook_torch.py
cryptolith/runtime.cpython-314-aarch64-linux-musl.so
cryptolith/virtualizer.cpython-314-aarch64-linux-musl.so
cryptolith-0.2.4.dist-info/licenses/LICENSE
cryptolith-0.2.4.dist-info/METADATA
cryptolith-0.2.4.dist-info/WHEEL
cryptolith-0.2.4.dist-info/entry_points.txt
cryptolith-0.2.4.dist-info/top_level.txt
cryptolith-0.2.4.dist-info/RECORD
