Metadata-Version: 2.4
Name: cryptolith
Version: 0.2.4
Summary: Advanced Python source code obfuscator and compiler protection.
Author-email: Massimo <massimo@example.com>
Project-URL: Homepage, https://github.com/Pietracoops/cryptolith
Classifier: Programming Language :: Python :: 3
Classifier: License :: Other/Proprietary License
Classifier: Operating System :: OS Independent
Requires-Python: >=3.7
License-File: LICENSE
Requires-Dist: pyinstaller
Requires-Dist: click
Requires-Dist: astunparse
Requires-Dist: cryptography
Dynamic: license-file
